{
	"inputs" : 
	[
		{
			"path" : "CMakeLists.txt"
		},
		{
			"isGenerated" : true,
			"path" : "F:/SeetaFace2/build-SeetaFace2-Desktop_Qt_5_14_2_MinGW_64_bit-Release/CMakeFiles/3.25.0/CMakeSystem.cmake"
		},
		{
			"isCMake" : true,
			"isExternal" : true,
			"path" : "F:/CMAKE/share/cmake-3.25/Modules/CMakeSystemSpecificInitialize.cmake"
		},
		{
			"isGenerated" : true,
			"path" : "F:/SeetaFace2/build-SeetaFace2-Desktop_Qt_5_14_2_MinGW_64_bit-Release/CMakeFiles/3.25.0/CMakeCCompiler.cmake"
		},
		{
			"isGenerated" : true,
			"path" : "F:/SeetaFace2/build-SeetaFace2-Desktop_Qt_5_14_2_MinGW_64_bit-Release/CMakeFiles/3.25.0/CMakeCXXCompiler.cmake"
		},
		{
			"isCMake" : true,
			"isExternal" : true,
			"path" : "F:/CMAKE/share/cmake-3.25/Modules/CMakeSystemSpecificInformation.cmake"
		},
		{
			"isCMake" : true,
			"isExternal" : true,
			"path" : "F:/CMAKE/share/cmake-3.25/Modules/CMakeGenericSystem.cmake"
		},
		{
			"isCMake" : true,
			"isExternal" : true,
			"path" : "F:/CMAKE/share/cmake-3.25/Modules/CMakeInitializeConfigs.cmake"
		},
		{
			"isCMake" : true,
			"isExternal" : true,
			"path" : "F:/CMAKE/share/cmake-3.25/Modules/Platform/Windows.cmake"
		},
		{
			"isCMake" : true,
			"isExternal" : true,
			"path" : "F:/CMAKE/share/cmake-3.25/Modules/Platform/WindowsPaths.cmake"
		},
		{
			"isCMake" : true,
			"isExternal" : true,
			"path" : "F:/CMAKE/share/cmake-3.25/Modules/CMakeFindCodeBlocks.cmake"
		},
		{
			"isCMake" : true,
			"isExternal" : true,
			"path" : "F:/CMAKE/share/cmake-3.25/Modules/CMakeExtraGeneratorDetermineCompilerMacrosAndIncludeDirs.cmake"
		},
		{
			"isCMake" : true,
			"isExternal" : true,
			"path" : "F:/CMAKE/share/cmake-3.25/Modules/ProcessorCount.cmake"
		},
		{
			"isCMake" : true,
			"isExternal" : true,
			"path" : "F:/CMAKE/share/cmake-3.25/Modules/CMakeCInformation.cmake"
		},
		{
			"isCMake" : true,
			"isExternal" : true,
			"path" : "F:/CMAKE/share/cmake-3.25/Modules/CMakeLanguageInformation.cmake"
		},
		{
			"isCMake" : true,
			"isExternal" : true,
			"path" : "F:/CMAKE/share/cmake-3.25/Modules/Compiler/GNU-C.cmake"
		},
		{
			"isCMake" : true,
			"isExternal" : true,
			"path" : "F:/CMAKE/share/cmake-3.25/Modules/Compiler/GNU.cmake"
		},
		{
			"isCMake" : true,
			"isExternal" : true,
			"path" : "F:/CMAKE/share/cmake-3.25/Modules/Compiler/CMakeCommonCompilerMacros.cmake"
		},
		{
			"isCMake" : true,
			"isExternal" : true,
			"path" : "F:/CMAKE/share/cmake-3.25/Modules/Platform/Windows-GNU-C.cmake"
		},
		{
			"isCMake" : true,
			"isExternal" : true,
			"path" : "F:/CMAKE/share/cmake-3.25/Modules/Platform/Windows-GNU.cmake"
		},
		{
			"isGenerated" : true,
			"path" : "F:/SeetaFace2/build-SeetaFace2-Desktop_Qt_5_14_2_MinGW_64_bit-Release/CMakeFiles/3.25.0/CMakeRCCompiler.cmake"
		},
		{
			"isCMake" : true,
			"isExternal" : true,
			"path" : "F:/CMAKE/share/cmake-3.25/Modules/CMakeRCInformation.cmake"
		},
		{
			"isCMake" : true,
			"isExternal" : true,
			"path" : "F:/CMAKE/share/cmake-3.25/Modules/Platform/Windows-windres.cmake"
		},
		{
			"isCMake" : true,
			"isExternal" : true,
			"path" : "F:/CMAKE/share/cmake-3.25/Modules/Platform/Windows-GNU-C-ABI.cmake"
		},
		{
			"isCMake" : true,
			"isExternal" : true,
			"path" : "F:/CMAKE/share/cmake-3.25/Modules/CMakeCommonLanguageInclude.cmake"
		},
		{
			"isCMake" : true,
			"isExternal" : true,
			"path" : "F:/CMAKE/share/cmake-3.25/Modules/CMakeCXXInformation.cmake"
		},
		{
			"isCMake" : true,
			"isExternal" : true,
			"path" : "F:/CMAKE/share/cmake-3.25/Modules/CMakeLanguageInformation.cmake"
		},
		{
			"isCMake" : true,
			"isExternal" : true,
			"path" : "F:/CMAKE/share/cmake-3.25/Modules/Compiler/GNU-CXX.cmake"
		},
		{
			"isCMake" : true,
			"isExternal" : true,
			"path" : "F:/CMAKE/share/cmake-3.25/Modules/Compiler/GNU.cmake"
		},
		{
			"isCMake" : true,
			"isExternal" : true,
			"path" : "F:/CMAKE/share/cmake-3.25/Modules/Platform/Windows-GNU-CXX.cmake"
		},
		{
			"isCMake" : true,
			"isExternal" : true,
			"path" : "F:/CMAKE/share/cmake-3.25/Modules/Platform/Windows-GNU.cmake"
		},
		{
			"isCMake" : true,
			"isExternal" : true,
			"path" : "F:/CMAKE/share/cmake-3.25/Modules/Platform/Windows-GNU-CXX-ABI.cmake"
		},
		{
			"isCMake" : true,
			"isExternal" : true,
			"path" : "F:/CMAKE/share/cmake-3.25/Modules/CMakeCommonLanguageInclude.cmake"
		},
		{
			"path" : "cmake/cmake_uninstall.cmake.in"
		},
		{
			"isCMake" : true,
			"isExternal" : true,
			"path" : "F:/CMAKE/share/cmake-3.25/Modules/CMakePackageConfigHelpers.cmake"
		},
		{
			"isCMake" : true,
			"isExternal" : true,
			"path" : "F:/CMAKE/share/cmake-3.25/Modules/WriteBasicConfigVersionFile.cmake"
		},
		{
			"isCMake" : true,
			"isExternal" : true,
			"path" : "F:/CMAKE/share/cmake-3.25/Modules/GNUInstallDirs.cmake"
		},
		{
			"isCMake" : true,
			"isExternal" : true,
			"path" : "F:/CMAKE/share/cmake-3.25/Modules/GenerateExportHeader.cmake"
		},
		{
			"isCMake" : true,
			"isExternal" : true,
			"path" : "F:/CMAKE/share/cmake-3.25/Modules/CheckCCompilerFlag.cmake"
		},
		{
			"isCMake" : true,
			"isExternal" : true,
			"path" : "F:/CMAKE/share/cmake-3.25/Modules/CheckCSourceCompiles.cmake"
		},
		{
			"isCMake" : true,
			"isExternal" : true,
			"path" : "F:/CMAKE/share/cmake-3.25/Modules/Internal/CheckSourceCompiles.cmake"
		},
		{
			"isCMake" : true,
			"isExternal" : true,
			"path" : "F:/CMAKE/share/cmake-3.25/Modules/Internal/CheckCompilerFlag.cmake"
		},
		{
			"isCMake" : true,
			"isExternal" : true,
			"path" : "F:/CMAKE/share/cmake-3.25/Modules/Internal/CheckFlagCommonConfig.cmake"
		},
		{
			"isCMake" : true,
			"isExternal" : true,
			"path" : "F:/CMAKE/share/cmake-3.25/Modules/Internal/CheckSourceCompiles.cmake"
		},
		{
			"isCMake" : true,
			"isExternal" : true,
			"path" : "F:/CMAKE/share/cmake-3.25/Modules/CMakeCheckCompilerFlagCommonPatterns.cmake"
		},
		{
			"isCMake" : true,
			"isExternal" : true,
			"path" : "F:/CMAKE/share/cmake-3.25/Modules/CheckCXXCompilerFlag.cmake"
		},
		{
			"isCMake" : true,
			"isExternal" : true,
			"path" : "F:/CMAKE/share/cmake-3.25/Modules/CheckCXXSourceCompiles.cmake"
		},
		{
			"isCMake" : true,
			"isExternal" : true,
			"path" : "F:/CMAKE/share/cmake-3.25/Modules/Internal/CheckSourceCompiles.cmake"
		},
		{
			"isCMake" : true,
			"isExternal" : true,
			"path" : "F:/CMAKE/share/cmake-3.25/Modules/Internal/CheckCompilerFlag.cmake"
		},
		{
			"isCMake" : true,
			"isExternal" : true,
			"path" : "F:/CMAKE/share/cmake-3.25/Modules/CheckIncludeFile.cmake"
		},
		{
			"isCMake" : true,
			"isExternal" : true,
			"path" : "F:/CMAKE/share/cmake-3.25/Modules/CheckIncludeFileCXX.cmake"
		},
		{
			"isCMake" : true,
			"isExternal" : true,
			"path" : "F:/CMAKE/share/cmake-3.25/Modules/CheckFunctionExists.cmake"
		},
		{
			"path" : "SeetaFace.pc.in"
		},
		{
			"path" : "SeetaNet/CMakeLists.txt"
		},
		{
			"isCMake" : true,
			"isExternal" : true,
			"path" : "F:/CMAKE/share/cmake-3.25/Modules/exportheader.cmake.in"
		},
		{
			"isCMake" : true,
			"isExternal" : true,
			"path" : "F:/CMAKE/share/cmake-3.25/Modules/BasicConfigVersion-AnyNewerVersion.cmake.in"
		},
		{
			"path" : "SeetaNet/SeetaNet.pc.in"
		},
		{
			"path" : "FaceDetector/CMakeLists.txt"
		},
		{
			"isCMake" : true,
			"isExternal" : true,
			"path" : "F:/CMAKE/share/cmake-3.25/Modules/exportheader.cmake.in"
		},
		{
			"isCMake" : true,
			"isExternal" : true,
			"path" : "F:/CMAKE/share/cmake-3.25/Modules/BasicConfigVersion-AnyNewerVersion.cmake.in"
		},
		{
			"path" : "FaceDetector/FaceDetector.pc.in"
		},
		{
			"path" : "FaceTracker/CMakeLists.txt"
		},
		{
			"isCMake" : true,
			"isExternal" : true,
			"path" : "F:/CMAKE/share/cmake-3.25/Modules/exportheader.cmake.in"
		},
		{
			"isCMake" : true,
			"isExternal" : true,
			"path" : "F:/CMAKE/share/cmake-3.25/Modules/BasicConfigVersion-AnyNewerVersion.cmake.in"
		},
		{
			"path" : "FaceTracker/FaceTracker.pc.in"
		},
		{
			"path" : "FaceLandmarker/CMakeLists.txt"
		},
		{
			"isCMake" : true,
			"isExternal" : true,
			"path" : "F:/CMAKE/share/cmake-3.25/Modules/exportheader.cmake.in"
		},
		{
			"isCMake" : true,
			"isExternal" : true,
			"path" : "F:/CMAKE/share/cmake-3.25/Modules/BasicConfigVersion-AnyNewerVersion.cmake.in"
		},
		{
			"path" : "FaceLandmarker/SeetaFaceLandmarker.pc.in"
		},
		{
			"path" : "FaceRecognizer/CMakeLists.txt"
		},
		{
			"isCMake" : true,
			"isExternal" : true,
			"path" : "F:/CMAKE/share/cmake-3.25/Modules/exportheader.cmake.in"
		},
		{
			"isCMake" : true,
			"isExternal" : true,
			"path" : "F:/CMAKE/share/cmake-3.25/Modules/BasicConfigVersion-AnyNewerVersion.cmake.in"
		},
		{
			"path" : "FaceRecognizer/FaceRecognizer.pc.in"
		},
		{
			"path" : "QualityAssessor/CMakeLists.txt"
		},
		{
			"isCMake" : true,
			"isExternal" : true,
			"path" : "F:/CMAKE/share/cmake-3.25/Modules/BasicConfigVersion-AnyNewerVersion.cmake.in"
		},
		{
			"path" : "QualityAssessor/QualityAssessor.pc.in"
		},
		{
			"path" : "example/CMakeLists.txt"
		},
		{
			"path" : "example/points81/CMakeLists.txt"
		},
		{
			"isExternal" : true,
			"path" : "F:/OpenCV_BY/OpenCVConfig-version.cmake"
		},
		{
			"isExternal" : true,
			"path" : "F:/OpenCV_BY/OpenCVConfig.cmake"
		},
		{
			"isExternal" : true,
			"path" : "F:/OpenCV_BY/x64/mingw/lib/OpenCVConfig.cmake"
		},
		{
			"isCMake" : true,
			"isExternal" : true,
			"path" : "F:/CMAKE/share/cmake-3.25/Modules/FindPackageHandleStandardArgs.cmake"
		},
		{
			"isCMake" : true,
			"isExternal" : true,
			"path" : "F:/CMAKE/share/cmake-3.25/Modules/FindPackageMessage.cmake"
		},
		{
			"isExternal" : true,
			"path" : "F:/OpenCV_BY/x64/mingw/lib/OpenCVModules.cmake"
		},
		{
			"isExternal" : true,
			"path" : "F:/OpenCV_BY/x64/mingw/lib/OpenCVModules-release.cmake"
		},
		{
			"path" : "example/search/CMakeLists.txt"
		},
		{
			"isExternal" : true,
			"path" : "F:/OpenCV_BY/OpenCVConfig-version.cmake"
		},
		{
			"isExternal" : true,
			"path" : "F:/OpenCV_BY/OpenCVConfig.cmake"
		},
		{
			"isExternal" : true,
			"path" : "F:/OpenCV_BY/x64/mingw/lib/OpenCVConfig.cmake"
		},
		{
			"isCMake" : true,
			"isExternal" : true,
			"path" : "F:/CMAKE/share/cmake-3.25/Modules/FindPackageHandleStandardArgs.cmake"
		},
		{
			"isCMake" : true,
			"isExternal" : true,
			"path" : "F:/CMAKE/share/cmake-3.25/Modules/FindPackageMessage.cmake"
		},
		{
			"isExternal" : true,
			"path" : "F:/OpenCV_BY/x64/mingw/lib/OpenCVModules.cmake"
		},
		{
			"isExternal" : true,
			"path" : "F:/OpenCV_BY/x64/mingw/lib/OpenCVModules-release.cmake"
		},
		{
			"path" : "example/tracking/CMakeLists.txt"
		},
		{
			"isExternal" : true,
			"path" : "F:/OpenCV_BY/OpenCVConfig-version.cmake"
		},
		{
			"isExternal" : true,
			"path" : "F:/OpenCV_BY/OpenCVConfig.cmake"
		},
		{
			"isExternal" : true,
			"path" : "F:/OpenCV_BY/x64/mingw/lib/OpenCVConfig.cmake"
		},
		{
			"isCMake" : true,
			"isExternal" : true,
			"path" : "F:/CMAKE/share/cmake-3.25/Modules/FindPackageHandleStandardArgs.cmake"
		},
		{
			"isCMake" : true,
			"isExternal" : true,
			"path" : "F:/CMAKE/share/cmake-3.25/Modules/FindPackageMessage.cmake"
		},
		{
			"isExternal" : true,
			"path" : "F:/OpenCV_BY/x64/mingw/lib/OpenCVModules.cmake"
		},
		{
			"isExternal" : true,
			"path" : "F:/OpenCV_BY/x64/mingw/lib/OpenCVModules-release.cmake"
		},
		{
			"path" : "example/crop_face/CMakeLists.txt"
		},
		{
			"isExternal" : true,
			"path" : "F:/OpenCV_BY/OpenCVConfig-version.cmake"
		},
		{
			"isExternal" : true,
			"path" : "F:/OpenCV_BY/OpenCVConfig.cmake"
		},
		{
			"isExternal" : true,
			"path" : "F:/OpenCV_BY/x64/mingw/lib/OpenCVConfig.cmake"
		},
		{
			"isCMake" : true,
			"isExternal" : true,
			"path" : "F:/CMAKE/share/cmake-3.25/Modules/FindPackageHandleStandardArgs.cmake"
		},
		{
			"isCMake" : true,
			"isExternal" : true,
			"path" : "F:/CMAKE/share/cmake-3.25/Modules/FindPackageMessage.cmake"
		},
		{
			"isExternal" : true,
			"path" : "F:/OpenCV_BY/x64/mingw/lib/OpenCVModules.cmake"
		},
		{
			"isExternal" : true,
			"path" : "F:/OpenCV_BY/x64/mingw/lib/OpenCVModules-release.cmake"
		}
	],
	"kind" : "cmakeFiles",
	"paths" : 
	{
		"build" : "F:/SeetaFace2/build-SeetaFace2-Desktop_Qt_5_14_2_MinGW_64_bit-Release",
		"source" : "F:/SeetaFace2/SeetaFace2"
	},
	"version" : 
	{
		"major" : 1,
		"minor" : 0
	}
}
